MANIFEST.in
README.rst
base.cfg
buildout.cfg
constraints.txt
constraints_plone52.txt
requirements.txt
setup.cfg
setup.py
test_plone52.cfg
collective/__init__.py
collective.limitfilesizepanel.egg-info/PKG-INFO
collective.limitfilesizepanel.egg-info/SOURCES.txt
collective.limitfilesizepanel.egg-info/dependency_links.txt
collective.limitfilesizepanel.egg-info/entry_points.txt
collective.limitfilesizepanel.egg-info/namespace_packages.txt
collective.limitfilesizepanel.egg-info/not-zip-safe
collective.limitfilesizepanel.egg-info/requires.txt
collective.limitfilesizepanel.egg-info/top_level.txt
collective/limitfilesizepanel/__init__.py
collective/limitfilesizepanel/configure.zcml
collective/limitfilesizepanel/dx_validators.py
collective/limitfilesizepanel/interfaces.py
collective/limitfilesizepanel/setuphandlers.py
collective/limitfilesizepanel/testing.py
collective/limitfilesizepanel/upgrades.zcml
collective/limitfilesizepanel/Extensions/install.py
collective/limitfilesizepanel/browser/__init__.py
collective/limitfilesizepanel/browser/configure.zcml
collective/limitfilesizepanel/browser/controlpanel.py
collective/limitfilesizepanel/browser/limitfilesizepanel_view.py
collective/limitfilesizepanel/browser/tinymce_upload_p5.py
collective/limitfilesizepanel/browser/images/limitfilesize-settings.png
collective/limitfilesizepanel/locales/collective.limitfilesizepanel-manual.pot
collective/limitfilesizepanel/locales/collective.limitfilesizepanel.pot
collective/limitfilesizepanel/locales/rebuildPo.sh
collective/limitfilesizepanel/locales/de/LC_MESSAGES/collective.limitfilesizepanel.mo
collective/limitfilesizepanel/locales/de/LC_MESSAGES/collective.limitfilesizepanel.po
collective/limitfilesizepanel/locales/it/LC_MESSAGES/collective.limitfilesizepanel.mo
collective/limitfilesizepanel/locales/it/LC_MESSAGES/collective.limitfilesizepanel.po
collective/limitfilesizepanel/profiles/default/browserlayer.xml
collective/limitfilesizepanel/profiles/default/controlpanel.xml
collective/limitfilesizepanel/profiles/default/metadata.xml
collective/limitfilesizepanel/profiles/default/registry.xml
collective/limitfilesizepanel/profiles/default/rolemap.xml
collective/limitfilesizepanel/profiles/uninstall/browserlayer.xml
collective/limitfilesizepanel/profiles/uninstall/controlpanel.xml
collective/limitfilesizepanel/profiles/uninstall/registry.xml
collective/limitfilesizepanel/tests/__init__.py
